httpie_odps_auth.py
setup.py
httpie_odps_auth.egg-info/PKG-INFO
httpie_odps_auth.egg-info/SOURCES.txt
httpie_odps_auth.egg-info/dependency_links.txt
httpie_odps_auth.egg-info/entry_points.txt
httpie_odps_auth.egg-info/not-zip-safe
httpie_odps_auth.egg-info/requires.txt
httpie_odps_auth.egg-info/top_level.txt